AUTHOR.txt
CHANGES.txt
LICENSE.txt
MANIFEST.in
bootstrap.py
buildout.cfg
setup.cfg
setup.py
src/biodec/__init__.py
src/biodec.recipe.riak.egg-info/PKG-INFO
src/biodec.recipe.riak.egg-info/SOURCES.txt
src/biodec.recipe.riak.egg-info/dependency_links.txt
src/biodec.recipe.riak.egg-info/entry_points.txt
src/biodec.recipe.riak.egg-info/namespace_packages.txt
src/biodec.recipe.riak.egg-info/not-zip-safe
src/biodec.recipe.riak.egg-info/requires.txt
src/biodec.recipe.riak.egg-info/top_level.txt
src/biodec/recipe/__init__.py
src/biodec/recipe/riak/README.txt
src/biodec/recipe/riak/__init__.py
src/biodec/recipe/riak/build.py
src/biodec/recipe/riak/instance.py
src/biodec/recipe/riak/tests/__init__.py
src/biodec/recipe/riak/tests/test_doc.py