Metadata-Version: 1.1
Name: biodec.recipe.riak
Version: 1.0.0a1
Summary: ZC Buildout recipe for setting up Riak.
Home-page: http://pypi.python.org/pypi/biodec.recipe.riak
Author: Mauro Amico
Author-email: mauro@biodec.com
License: LGPL 3
Keywords: riak zc.buildout recipe
Platform: UNKNOWN
Classifier: Development Status :: 3 - Alpha
Classifier: Framework :: Buildout
Classifier: Intended Audience :: Developers
Classifier: License :: OSI Approved :: GNU Library or Lesser General Public License (LGPL)
Classifier: Operating System :: POSIX
Classifier: Topic :: Software Development :: Build Tools
Classifier: Topic :: Software Development :: Libraries :: Python Modules
